{
	"folders": {},
	"connections": {
		"postgres-jdbc-199be293f84-69d78c590f0dbfb1": {
			"provider": "postgresql",
			"driver": "postgres-jdbc",
			"name": "springboot_db",
			"save-password": true,
			"configuration": {
				"host": "localhost",
				"port": "55433",
				"database": "springboot_db",
				"url": "jdbc:postgresql://localhost:55433/springboot_db",
				"configurationType": "MANUAL",
				"home": "/opt/homebrew/Cellar/postgresql@14/14.17_1",
				"type": "dev",
				"closeIdleConnection": true,
				"provider-properties": {
					"@dbeaver-show-non-default-db@": "false"
				},
				"auth-model": "native"
			}
		},
		"postgres-jdbc-199d98eb6ba-2d9dd597b0bbbaaa": {
			"provider": "postgresql",
			"driver": "postgres-jdbc",
			"name": "ecommerce-db",
			"save-password": true,
			"configuration": {
				"host": "localhost",
				"port": "55433",
				"database": "ecommerce-db",
				"url": "jdbc:postgresql://localhost:55433/ecommerce-db",
				"configurationType": "MANUAL",
				"home": "/opt/homebrew/Cellar/postgresql@14/14.17_1",
				"type": "dev",
				"closeIdleConnection": true,
				"provider-properties": {
					"@dbeaver-show-non-default-db@": "false"
				},
				"auth-model": "native"
			}
		},
		"postgres-jdbc-199f27a4916-409b6eca0b9793ab": {
			"provider": "postgresql",
			"driver": "postgres-jdbc",
			"name": "relations-db",
			"save-password": true,
			"configuration": {
				"host": "localhost",
				"port": "55433",
				"database": "relations-db",
				"url": "jdbc:postgresql://localhost:55433/relations-db",
				"configurationType": "MANUAL",
				"home": "/opt/homebrew/Cellar/postgresql@14/14.17_1",
				"type": "dev",
				"closeIdleConnection": true,
				"provider-properties": {
					"@dbeaver-show-non-default-db@": "false"
				},
				"auth-model": "native"
			}
		},
		"postgres-jdbc-199f27b806c-2860cb1cede446f5": {
			"provider": "postgresql",
			"driver": "postgres-jdbc",
			"name": "relations-db 2",
			"save-password": true,
			"configuration": {
				"host": "localhost",
				"port": "55433",
				"database": "relations-db",
				"url": "jdbc:postgresql://localhost:55433/relations-db",
				"configurationType": "MANUAL",
				"home": "/opt/homebrew/Cellar/postgresql@14/14.17_1",
				"type": "dev",
				"closeIdleConnection": true,
				"provider-properties": {
					"@dbeaver-show-non-default-db@": "false"
				},
				"auth-model": "native"
			}
		}
	},
	"connection-types": {
		"dev": {
			"name": "Development",
			"color": "255,255,255",
			"description": "Regular development database",
			"auto-commit": true,
			"confirm-execute": false,
			"confirm-data-change": false,
			"smart-commit": false,
			"smart-commit-recover": true,
			"auto-close-transactions": true,
			"close-transactions-period": 1800,
			"auto-close-connections": true,
			"close-connections-period": 14400
		}
	}
}